samclipdiffusion/__init__.py
samclipdiffusion/image_segmenter.py
samclipdiffusion/guided_diffusion_pipeline/__init__.py
samclipdiffusion-0.0.3b0.dist-info/METADATA
samclipdiffusion-0.0.3b0.dist-info/WHEEL
samclipdiffusion-0.0.3b0.dist-info/top_level.txt
samclipdiffusion-0.0.3b0.dist-info/RECORD
