Metadata-Version: 2.1
Name: samclipdiffusion
Version: 0.0.3b0
Summary: A package for clip-guided diffusion
Home-page: https://github.com/eren23/sam-clip-diffusion
Author: Eren Akbulut
Author-email: erenakbulutwork@gmail.com
License: UNKNOWN
Platform: UNKNOWN
Classifier: Development Status :: 3 - Alpha
Classifier: Intended Audience :: Developers
Classifier: Intended Audience :: Science/Research
Classifier: License :: OSI Approved :: MIT License
Classifier: Programming Language :: Python :: 3
Classifier: Programming Language :: Python :: 3.7
Classifier: Programming Language :: Python :: 3.8
Classifier: Programming Language :: Python :: 3.9
Classifier: Topic :: Scientific/Engineering :: Artificial Intelligence
Requires-Dist: torch
Requires-Dist: opencv-python
Requires-Dist: Pillow
Requires-Dist: diffusers
Requires-Dist: transformers
Requires-Dist: accelerate
